Metadata-Version: 1.1
Name: forseti
Version: 0.8.0
Summary: Formal Logic Framework
Home-page: https://github.com/MasterOdin/forseti
Author: Matthew Peveler
Author-email: matt.peveler@gmail.com
License: MIT
Download-URL: https://pypi.python.org/pypi/forseti
Platform: UNKNOWN
Classifier: Development Status :: 4 - Beta
Classifier: Intended Audience :: Developers
Classifier: Intended Audience :: Science/Research
Classifier: License :: OSI Approved :: MIT License
Classifier: Natural Language :: English
Classifier: Operating System :: OS Independent
Classifier: Programming Language :: Python
Classifier: Programming Language :: Python :: 2.7
Classifier: Programming Language :: Python :: 3.3
Classifier: Programming Language :: Python :: 3.4
Classifier: Operating System :: OS Independent
Classifier: Topic :: Scientific/Engineering :: Mathematics
